floofyredpanda/__init__.py
floofyredpanda/client.py
floofyredpanda/server.py
floofyredpanda/utils.py
floofyredpanda-1.0.7.dist-info/METADATA
floofyredpanda-1.0.7.dist-info/WHEEL
floofyredpanda-1.0.7.dist-info/top_level.txt
floofyredpanda-1.0.7.dist-info/RECORD
