Metadata-Version: 2.4
Name: floofyredpanda
Version: 1.0.7
Summary: A delightfully unhinged socket library with SSL support and caveman energy
Author: shadow113323 
License: MIT
Project-URL: Homepage, https://pypi.org/project/floofyredpanda/
Keywords: socket,ssl,floof,panda,networking,fun
Classifier: Development Status :: 4 - Beta
Classifier: Intended Audience :: Developers
Classifier: Programming Language :: Python :: 3.12
Classifier: Topic :: Internet
Classifier: Topic :: Software Development :: Libraries :: Python Modules
Classifier: Topic :: System :: Networking
Requires-Python: >=3.7
